llm_xml_parser/__init__.py
llm_xml_parser/core/__init__.py
llm_xml_parser/core/lexer.py
llm_xml_parser/core/parser.py
llm_xml_parser/core/validator.py
llm_xml_parser/exceptions/__init__.py
llm_xml_parser/exceptions/errors.py
llm_xml_parser/exceptions/warnings.py
llm_xml_parser/structures/__init__.py
llm_xml_parser/structures/config.py
llm_xml_parser/structures/node.py
llm_xml_parser/structures/result.py
llm_xml_parser/utils/__init__.py
llm_xml_parser/utils/logger.py
llm_xml_parser/utils/preprocessor.py
xml_parser_llm-0.1.1.dist-info/LICENSE
xml_parser_llm-0.1.1.dist-info/METADATA
xml_parser_llm-0.1.1.dist-info/WHEEL
xml_parser_llm-0.1.1.dist-info/RECORD
