Metadata-Version: 2.1
Name: xml-parser-llm
Version: 0.1.1
Summary: A minimal XML parser for structured output from LLM
License: MIT
Author: edoardoavenia
Author-email: aveniaedoardo1@gmail.com
Requires-Python: >=3.13,<4.0
Classifier: License :: OSI Approved :: MIT License
Classifier: Programming Language :: Python :: 3
Classifier: Programming Language :: Python :: 3.13
